fvm/__init__.py
fvm/argument_parser.py
fvm/framework.py
fvm/generate_test_cases.py
fvm/helpers.py
fvm/logcounter.py
fvm/manage_allure.py
fvm/reports.py
fvm/steps.py
fvm/tables.py
fvm/assets/FVM_logo_192x192.png
fvm/assets/favicon.ico
fvm/drom2psl/__init__.py
fvm/drom2psl/basiclogging.py
fvm/drom2psl/definitions.py
fvm/drom2psl/generator.py
fvm/drom2psl/interpret.py
fvm/drom2psl/traverse.py
fvm/toolchains/__init__.py
fvm/toolchains/questa.py
fvm/toolchains/toolchains.py
fvm/toolchains/questa_pkg/__init__.py
fvm/toolchains/questa_pkg/parsers/__init__.py
fvm/toolchains/questa_pkg/parsers/parse_clocks.py
fvm/toolchains/questa_pkg/parsers/parse_design_rpt.py
fvm/toolchains/questa_pkg/parsers/parse_formal_signoff.py
fvm/toolchains/questa_pkg/parsers/parse_lint.py
fvm/toolchains/questa_pkg/parsers/parse_prove.py
fvm/toolchains/questa_pkg/parsers/parse_reachability.py
fvm/toolchains/questa_pkg/parsers/parse_reports.py
fvm/toolchains/questa_pkg/parsers/parse_resets.py
fvm/toolchains/questa_pkg/parsers/parse_rulecheck.py
fvm/toolchains/questa_pkg/parsers/parse_simcover.py
fvm/toolchains/questa_pkg/parsers/parse_xverify.py
fvm_formal-0.1.16.dist-info/licenses/LICENSE
fvm_formal-0.1.16.dist-info/METADATA
fvm_formal-0.1.16.dist-info/WHEEL
fvm_formal-0.1.16.dist-info/entry_points.txt
fvm_formal-0.1.16.dist-info/top_level.txt
fvm_formal-0.1.16.dist-info/RECORD
