Metadata-Version: 2.4
Name: fvm-formal
Version: 0.1.16
Summary: A Formal Verification Methodology for ASIC and FPGA designs
Author-email: Hipolito Guzmán-Miranda <hguzman@us.es>, Marcos López García <marlopgar40@alum.us.es>
License-Expression: Apache-2.0
Project-URL: homepage, https://fvm.us.es
Requires-Python: >=3.9
License-File: LICENSE
Requires-Dist: icecream>=2.1.3
Requires-Dist: junit-xml>=1.9
Requires-Dist: loguru>=0.7.3
Requires-Dist: pathlib>=1.0.1
Requires-Dist: pyyaml>=6.0.3
Requires-Dist: rich>=14.2.0
Requires-Dist: termcolor>=3.1.0
Requires-Dist: wavedrom>=2.0.3.post3
Dynamic: license-file
